AERes/__init__.py
AERes/attention.py
AERes/dynamicalSystems.py
AERes/reservoir.py
AERes-0.1.3.dist-info/LICENSE
AERes-0.1.3.dist-info/METADATA
AERes-0.1.3.dist-info/WHEEL
AERes-0.1.3.dist-info/top_level.txt
AERes-0.1.3.dist-info/RECORD
