Metadata-Version: 2.1
Name: AERes
Version: 0.1.3
Summary: A Python library for dynamical systems, reservoir computing, and attention mechanisms.
Home-page: https://github.com/Rincewind1989/AERes
Author: Felix Köster
Author-email: felixk@mail.saitama-u.ac.jp
License: UNKNOWN
Project-URL: Bug Tracker, https://github.com/Rincewind1989/AERes/issues
Platform: UNKNOWN
Classifier: Programming Language :: Python :: 3
Classifier: License :: OSI Approved :: MIT License
Classifier: Operating System :: OS Independent
Requires-Python: >=3.6
License-File: LICENSE
Requires-Dist: numpy
Requires-Dist: scipy
Requires-Dist: torch
